CHANGES.rst
MANIFEST.in
README.rst
setup.cfg
setup.py
docs/LICENSE.GPL
docs/LICENSE.txt
src/lineage/__init__.py
src/lineage.index.egg-info/PKG-INFO
src/lineage.index.egg-info/SOURCES.txt
src/lineage.index.egg-info/dependency_links.txt
src/lineage.index.egg-info/entry_points.txt
src/lineage.index.egg-info/namespace_packages.txt
src/lineage.index.egg-info/not-zip-safe
src/lineage.index.egg-info/requires.txt
src/lineage.index.egg-info/top_level.txt
src/lineage/index/__init__.py
src/lineage/index/configure.zcml
src/lineage/index/index.py
src/lineage/index/upgrades.py
src/lineage/index/view.py
src/lineage/index/vocabulary.py
src/lineage/index/profiles/default/catalog.xml
src/lineage/index/profiles/default/metadata.xml
src/lineage/index/profiles/uninstall/catalog.xml